setup.py
sphinxcontrib/__init__.py
sphinxcontrib/swaggerui/__init__.py
sphinxcontrib/swaggerui/swaggerui.py
sphinxcontrib_swaggerui-0.1.0.dist-info/METADATA
sphinxcontrib_swaggerui-0.1.0.dist-info/WHEEL
sphinxcontrib_swaggerui-0.1.0.dist-info/licenses/LICENSE
sphinxcontrib_swaggerui-0.1.0.dist-info/RECORD
