Metadata-Version: 2.1
Name: sphinxcontrib-swaggerui
Version: 0.1.0
Summary: Provides the swaggerui directive for reST files to build an interactive HTML page with your OpenAPI specification document.
Project-URL: Homepage, https://bitbucket.org/albert_bagdasaryan/sphinxcontrib-swaggerui/
Project-URL: Bug Tracker, https://bitbucket.org/albert_bagdasaryan/sphinxcontrib-swaggerui/jira
Author-email: Albert Bagdasaryan <albert.bagd@gmail.com>
License-File: LICENSE
Classifier: License :: OSI Approved :: MIT License
Classifier: Operating System :: OS Independent
Classifier: Programming Language :: Python :: 3
Requires-Python: >=3.8
